mandelbrot_julia_fractals/__init__.py
mandelbrot_julia_fractals/fractals.py
mandelbrot_julia_fractals/mandelbrot_3d_opengl.py
mandelbrot_julia_fractals/widgets.py
mandelbrot_julia_fractals-1.0.2.dist-info/LICENSE
mandelbrot_julia_fractals-1.0.2.dist-info/METADATA
mandelbrot_julia_fractals-1.0.2.dist-info/WHEEL
mandelbrot_julia_fractals-1.0.2.dist-info/top_level.txt
mandelbrot_julia_fractals-1.0.2.dist-info/RECORD
