Metadata-Version: 2.1
Name: mandelbrot-julia-fractals
Version: 1.0.2
Summary: A fractal visualisation for the Mandelbrot and Julia sets
Home-page: https://github.com/LayanJethwa/fractals
Author: Layan Jethwa
Author-email: lrsjethwa3.14@gmail.com
Classifier: Programming Language :: Python :: 3.10
Classifier: License :: OSI Approved :: MIT License
Classifier: Operating System :: OS Independent
License-File: LICENSE
Requires-Dist: colour (==0.1.5)
Requires-Dist: cupy-cuda13x (==13.6.0)
Requires-Dist: numpy (==2.1.1)
Requires-Dist: pygame (==2.1.2)
Requires-Dist: PyOpenGL (==3.1.10)
